{"rules_cheat.md":"44b9bbdc","course_residence.md":"c637eb81","index.md":"c3fed11a","join-game_client.md":"55cc73c2","join-game_help.md":"f1de7535","join-game_info.md":"a7e33cc2","course_crackshot.md":"505b9d5b","course_mcmmo.md":"6e3992ef","course_mcbbs.md":"5b599cb9","course_advancedenchantments.md":"37783b9e","course_brewery.md":"72425869","course_base.md":"84f54cc0","join-game_resourcepack.md":"d700ad37","rules_agreement.md":"82b34b08","support_index.md":"631a0baa","update-logs_client-c.md":"e22ffe64","update-logs_client-i_c.md":"fd79e68c","update-logs_resourcepack.md":"0aa06dc3","update-logs_server.md":"57d77e6c"}
